LICENSE
MANIFEST.in
README.rst
requirements.txt
setup.py
LICENSES/JOBLIB_LICENSE
LICENSES/PANDAS_LICENSE
LICENSES/PYPRIND_LICENSE
LICENSES/PY_STRINGMATCHING_LICENSE
LICENSES/SIX_LICENSE
dummy_package1/__init__.py
dummy_package1.egg-info/PKG-INFO
dummy_package1.egg-info/SOURCES.txt
dummy_package1.egg-info/dependency_links.txt
dummy_package1.egg-info/not-zip-safe
dummy_package1.egg-info/requires.txt
dummy_package1.egg-info/top_level.txt
dummy_package1/datasets/__init__.py
dummy_package1/datasets/base.py
dummy_package1/filter/__init__.py
dummy_package1/filter/filter.py
dummy_package1/filter/filter_utils.py
dummy_package1/filter/overlap_filter.py
dummy_package1/filter/position_filter.py
dummy_package1/filter/prefix_filter.py
dummy_package1/filter/size_filter.py
dummy_package1/filter/suffix_filter.py
dummy_package1/index/__init__.py
dummy_package1/index/index.py
dummy_package1/index/inverted_index.py
dummy_package1/index/position_index.py
dummy_package1/index/prefix_index.py
dummy_package1/index/size_index.py
dummy_package1/join/__init__.py
dummy_package1/join/cosine_join.py
dummy_package1/join/dice_join.py
dummy_package1/join/edit_distance_join.py
dummy_package1/join/jaccard_join.py
dummy_package1/join/overlap_coefficient_join.py
dummy_package1/join/overlap_join.py
dummy_package1/join/set_sim_join.py
dummy_package1/matcher/__init__.py
dummy_package1/matcher/apply_matcher.py
dummy_package1/profiler/__init__.py
dummy_package1/profiler/profiler.py
dummy_package1/tests/__init__.py
dummy_package1/tests/test_apply_matcher.py
dummy_package1/tests/test_converter_utils.py
dummy_package1/tests/test_edit_dist_join.py
dummy_package1/tests/test_helper_functions.py
dummy_package1/tests/test_join.py
dummy_package1/tests/test_overlap_filter.py
dummy_package1/tests/test_overlap_join.py
dummy_package1/tests/test_position_filter.py
dummy_package1/tests/test_prefix_filter.py
dummy_package1/tests/test_profiler.py
dummy_package1/tests/test_size_filter.py
dummy_package1/tests/test_suffix_filter.py
dummy_package1/utils/__init__.py
dummy_package1/utils/converter.py
dummy_package1/utils/generic_helper.py
dummy_package1/utils/missing_value_handler.py
dummy_package1/utils/pickle.py
dummy_package1/utils/simfunctions.py
